Paquetes/Paquete.py
Paquete_axir-1.0.dist-info/METADATA
Paquete_axir-1.0.dist-info/WHEEL
Paquete_axir-1.0.dist-info/top_level.txt
Paquete_axir-1.0.dist-info/RECORD
