Metadata-Version: 2.1
Name: Paquete-axir
Version: 1.0
Summary: A useful module
Author: DaniQB
